<Properties StartupConfiguration="{7A88B1D1-32D1-4225-913A-68DBEA4E65EA}|Default">
  <MonoDevelop.Ide.ItemProperties.CmsLocalization PreferredExecutionTarget="MonoDevelop.Default" />
  <MonoDevelop.Ide.Workbench />
  <MonoDevelop.Ide.DebuggingService.PinnedWatches />
  <MonoDevelop.Ide.Workspace ActiveConfiguration="Debug" />
  <MonoDevelop.Ide.DebuggingService.Breakpoints>
    <BreakpointStore />
  </MonoDevelop.Ide.DebuggingService.Breakpoints>
  <MultiItemStartupConfigurations />
</Properties>